MANIFEST.in
distribute_setup.py
setup.py
docs/EN/Makefile
docs/EN/build/doctrees/changelog.doctree
docs/EN/build/doctrees/configuration.doctree
docs/EN/build/doctrees/daemon.doctree
docs/EN/build/doctrees/dont_do_that.doctree
docs/EN/build/doctrees/environment.pickle
docs/EN/build/doctrees/getting_started.doctree
docs/EN/build/doctrees/index.doctree
docs/EN/build/doctrees/introduction.doctree
docs/EN/build/doctrees/permissions.doctree
docs/EN/build/doctrees/rebuilding.doctree
docs/EN/build/doctrees/testing.doctree
docs/EN/build/html/.buildinfo
docs/EN/build/html/changelog.html
docs/EN/build/html/configuration.html
docs/EN/build/html/daemon.html
docs/EN/build/html/dont_do_that.html
docs/EN/build/html/genindex.html
docs/EN/build/html/getting_started.html
docs/EN/build/html/index.html
docs/EN/build/html/introduction.html
docs/EN/build/html/objects.inv
docs/EN/build/html/permissions.html
docs/EN/build/html/rebuilding.html
docs/EN/build/html/search.html
docs/EN/build/html/searchindex.js
docs/EN/build/html/testing.html
docs/EN/build/html/_images/pacha_light.jpg
docs/EN/build/html/_sources/changelog.txt
docs/EN/build/html/_sources/configuration.txt
docs/EN/build/html/_sources/daemon.txt
docs/EN/build/html/_sources/dont_do_that.txt
docs/EN/build/html/_sources/getting_started.txt
docs/EN/build/html/_sources/index.txt
docs/EN/build/html/_sources/introduction.txt
docs/EN/build/html/_sources/permissions.txt
docs/EN/build/html/_sources/rebuilding.txt
docs/EN/build/html/_sources/testing.txt
docs/EN/build/html/_static/basic.css
docs/EN/build/html/_static/default.css
docs/EN/build/html/_static/doctools.js
docs/EN/build/html/_static/file.png
docs/EN/build/html/_static/jquery.js
docs/EN/build/html/_static/minus.png
docs/EN/build/html/_static/pacha.jpg
docs/EN/build/html/_static/pacha_light.jpg
docs/EN/build/html/_static/plus.png
docs/EN/build/html/_static/pygments.css
docs/EN/build/html/_static/searchtools.js
docs/EN/build/html/_static/sidebar.js
pacha.egg-info/PKG-INFO
pacha.egg-info/SOURCES.txt
pacha.egg-info/dependency_links.txt
pacha.egg-info/entry_points.txt
pacha.egg-info/requires.txt
pacha.egg-info/top_level.txt
