Metadata-Version: 1.0
Name: pacha
Version: 0.3.1
Summary: Systems configuration/management engine
Home-page: http://pacha.cafepais.com
Author: Alfredo Deza
Author-email: alfredodeza [at] gmail [dot] com
License: MIT
Keywords: systems configuration management engine hg mercurial
Platform: UNKNOWN
Classifier: Development Status :: 4 - Beta
Classifier: Intended Audience :: Developers
Classifier: License :: OSI Approved :: MIT License
Classifier: Topic :: Software Development :: Build Tools
Classifier: Programming Language :: Python :: 2.5
Classifier: Programming Language :: Python :: 2.6
Classifier: Programming Language :: Python :: 2.7
